btreefilereader/ByBTree/filter_by.py
btreefilereader/__init__.py
btreefilereader/core/__init__.py
btreefilereader/core/__main__.py
btreefilereader/core/metadata.toml
btreefilereader/core/models.py
btreefilereader/core/reader_txt.py
btreefilereader-1.1.2.dist-info/LICENSE
btreefilereader-1.1.2.dist-info/METADATA
btreefilereader-1.1.2.dist-info/WHEEL
btreefilereader-1.1.2.dist-info/RECORD
