Metadata-Version: 2.1
Name: btreefilereader
Version: 1.1.2
Summary: B3 txt file reader and filter.
License: MIT
Author: João Marcos
Author-email: joaomarcosrs40@gmail.com
Requires-Python: >=3.12,<4.0
Classifier: License :: OSI Approved :: MIT License
Classifier: Programming Language :: Python :: 3
Classifier: Programming Language :: Python :: 3.12
Requires-Dist: pandas (>=2.0.0,<3.0.0)
Project-URL: Homepage, https://github.com/joaomarcosrs/btreefilereader
